{
  "$id": "1",
  "events": {
    "$id": "2",
    "$values": [
      {
        "$id": "3",
        "eventId": "0b959599-3867-481b-927f-e2a46e0d0e8a",
        "eventOccurenceId": null,
        "creatorId": "d7965476-6b0d-4ee1-be67-c67626b7ced6",
        "calendarId": "8e583741-ffa5-4915-98c0-2d1e6cbda527",
        "eventTypeId": "07a68346-a516-45c7-9b7a-66f8fba11b3d",
        "startTime": "2025-06-12T09:00:00Z",
        "endTime": "2025-06-12T10:00:00Z",
        "startDate": "2025-06-12",
        "endDate": "2025-06-12",
        "timeZone": "Africa/Lagos",
        "title": "test",
        "description": "",
        "eventOwner": "Not Available",
        "meetingLink": "",
        "bannerImage": "https://vecapp-bucket-dev.s3.amazonaws.com/demo/calendar/527f4cbe-19e6-422f-8c10-31ea9c9472ec.png",
        "meetingRoom": "",
        "additionalInfo": "",
        "noAttendeeHasResponded": true,
        "attendeesCount": 0,
        "responseCount": 0,
        "yesCount": 0,
        "noCount": 0,
        "maybeCount": 0,
        "isAllDay": false,
        "isSameDay": true,
        "venueAddress": "",
        "venueName": "",
        "eventClass": "Group",
        "eventStatus": "Ended",
        "individualCalendar": null,
        "teamCalendar": null,
        "groupCalendar": null,
        "eventTeams": {
          "$id": "4",
          "$values": []
        },
        "eventGroups": {
          "$id": "5",
          "$values": []
        },
        "eventSettings": {
          "$id": "6",
          "visibility": "private",
          "eventOccurence": "None",
          "recurrenceEnd": null,
          "eventEnds": false,
          "reminders": {
            "$id": "7",
            "$values": []
          }
        },
        "attendees": {
          "$id": "8",
          "$values": []
        },
        "resources": {
          "$id": "9",
          "$values": []
        },
        "eventSeries": {
          "$id": "10",
          "$values": []
        }
      },
      {
        "$id": "11",
        "eventId": "227b8ae6-8caa-4b1a-b174-304c783e87dd",
        "eventOccurenceId": null,
        "creatorId": "d7965476-6b0d-4ee1-be67-c67626b7ced6",
        "calendarId": "d51fa295-09ae-4a74-9bf0-4c91ab6d47f9",
        "eventTypeId": "07a68346-a516-45c7-9b7a-66f8fba11b3d",
        "startTime": "2025-07-23T15:00:00Z",
        "endTime": "2025-07-23T16:00:00Z",
        "startDate": "2025-07-23",
        "endDate": "2025-07-23",
        "timeZone": "America/Chicago",
        "title": "General meeting",
        "description": "",
        "eventOwner": "Not Available",
        "meetingLink": "",
        "bannerImage": "https://vecap-bucket.s3.amazonaws.com/demo/calendar/default_banner.png",
        "meetingRoom": "",
        "additionalInfo": "",
        "noAttendeeHasResponded": true,
        "attendeesCount": 0,
        "responseCount": 0,
        "yesCount": 0,
        "noCount": 0,
        "maybeCount": 0,
        "isAllDay": false,
        "isSameDay": true,
        "venueAddress": "",
        "venueName": "",
        "eventClass": "Team",
        "eventStatus": "Upcoming",
        "individualCalendar": null,
        "teamCalendar": null,
        "groupCalendar": null,
        "eventTeams": {
          "$id": "12",
          "$values": []
        },
        "eventGroups": {
          "$id": "13",
          "$values": []
        },
        "eventSettings": {
          "$id": "14",
          "visibility": "private",
          "eventOccurence": "None",
          "recurrenceEnd": null,
          "eventEnds": false,
          "reminders": {
            "$id": "15",
            "$values": []
          }
        },
        "attendees": {
          "$id": "16",
          "$values": []
        },
        "resources": {
          "$id": "17",
          "$values": []
        },
        "eventSeries": {
          "$id": "18",
          "$values": []
        }
      },
      {
        "$id": "19",
        "eventId": "7d1c9baf-00ab-49f7-a576-c9854dc5e8d3",
        "eventOccurenceId": null,
        "creatorId": "d7965476-6b0d-4ee1-be67-c67626b7ced6",
        "calendarId": "64ff7caa-ca20-4d93-88e7-5798fb20d6c1",
        "eventTypeId": "07a68346-a516-45c7-9b7a-66f8fba11b3d",
        "startTime": "2025-06-10T13:00:00Z",
        "endTime": "2025-06-10T14:00:00Z",
        "startDate": "2025-06-10",
        "endDate": "2025-06-10",
        "timeZone": "Africa/Lagos",
        "title": "Image",
        "description": "",
        "eventOwner": "Not Available",
        "meetingLink": "",
        "bannerImage": "https://vecapp-bucket-dev.s3.amazonaws.com/demo/calendar/35a85848-e1a1-45da-97d7-e411252f1b15.png",
        "meetingRoom": "",
        "additionalInfo": "",
        "noAttendeeHasResponded": true,
        "attendeesCount": 0,
        "responseCount": 0,
        "yesCount": 0,
        "noCount": 0,
        "maybeCount": 0,
        "isAllDay": false,
        "isSameDay": true,
        "venueAddress": "",
        "venueName": "",
        "eventClass": "Personal",
        "eventStatus": "Ended",
        "individualCalendar": null,
        "teamCalendar": null,
        "groupCalendar": null,
        "eventTeams": {
          "$id": "20",
          "$values": []
        },
        "eventGroups": {
          "$id": "21",
          "$values": []
        },
        "eventSettings": {
          "$id": "22",
          "visibility": "private",
          "eventOccurence": "None",
          "recurrenceEnd": null,
          "eventEnds": false,
          "reminders": {
            "$id": "23",
            "$values": []
          }
        },
        "attendees": {
          "$id": "24",
          "$values": []
        },
        "resources": {
          "$id": "25",
          "$values": []
        },
        "eventSeries": {
          "$id": "26",
          "$values": []
        }
      },
      {
        "$id": "27",
        "eventId": "28e77e81-cb86-401c-9175-304e82ef2730",
        "eventOccurenceId": null,
        "creatorId": "d7965476-6b0d-4ee1-be67-c67626b7ced6",
        "calendarId": "64ff7caa-ca20-4d93-88e7-5798fb20d6c1",
        "eventTypeId": "07a68346-a516-45c7-9b7a-66f8fba11b3d",
        "startTime": "2025-06-12T14:00:00Z",
        "endTime": "2025-06-12T15:00:00Z",
        "startDate": "2025-06-12",
        "endDate": "2025-06-12",
        "timeZone": "Africa/Lagos",
        "title": "test",
        "description": "",
        "eventOwner": "Not Available",
        "meetingLink": null,
        "bannerImage": "https://vecap-bucket.s3.amazonaws.com/demo/calendar/default_banner.png",
        "meetingRoom": null,
        "additionalInfo": "",
        "noAttendeeHasResponded": true,
        "attendeesCount": 0,
        "responseCount": 0,
        "yesCount": 0,
        "noCount": 0,
        "maybeCount": 0,
        "isAllDay": false,
        "isSameDay": true,
        "venueAddress": null,
        "venueName": null,
        "eventClass": "Personal",
        "eventStatus": "Ended",
        "individualCalendar": null,
        "teamCalendar": null,
        "groupCalendar": null,
        "eventTeams": {
          "$id": "28",
          "$values": []
        },
        "eventGroups": {
          "$id": "29",
          "$values": []
        },
        "eventSettings": {
          "$id": "30",
          "visibility": "private",
          "eventOccurence": "None",
          "recurrenceEnd": null,
          "eventEnds": false,
          "reminders": {
            "$id": "31",
            "$values": []
          }
        },
        "attendees": {
          "$id": "32",
          "$values": []
        },
        "resources": {
          "$id": "33",
          "$values": []
        },
        "eventSeries": {
          "$id": "34",
          "$values": []
        }
      },
      {
        "$id": "35",
        "eventId": "0263706c-37f8-4c96-8ceb-cfc0b6790317",
        "eventOccurenceId": null,
        "creatorId": "d7965476-6b0d-4ee1-be67-c67626b7ced6",
        "calendarId": "64ff7caa-ca20-4d93-88e7-5798fb20d6c1",
        "eventTypeId": "07a68346-a516-45c7-9b7a-66f8fba11b3d",
        "startTime": "2025-06-12T18:00:00Z",
        "endTime": "2025-06-12T19:00:00Z",
        "startDate": "2025-06-12",
        "endDate": "2025-06-12",
        "timeZone": "Africa/Lagos",
        "title": "jjjjjj",
        "description": "",
        "eventOwner": "Not Available",
        "meetingLink": "",
        "bannerImage": "https://vecap-bucket.s3.amazonaws.com/demo/calendar/default_banner.png",
        "meetingRoom": "",
        "additionalInfo": "",
        "noAttendeeHasResponded": true,
        "attendeesCount": 0,
        "responseCount": 0,
        "yesCount": 0,
        "noCount": 0,
        "maybeCount": 0,
        "isAllDay": false,
        "isSameDay": true,
        "venueAddress": "",
        "venueName": "",
        "eventClass": "Personal",
        "eventStatus": "Ended",
        "individualCalendar": null,
        "teamCalendar": null,
        "groupCalendar": null,
        "eventTeams": {
          "$id": "36",
          "$values": []
        },
        "eventGroups": {
          "$id": "37",
          "$values": []
        },
        "eventSettings": {
          "$id": "38",
          "visibility": "private",
          "eventOccurence": "None",
          "recurrenceEnd": null,
          "eventEnds": false,
          "reminders": {
            "$id": "39",
            "$values": []
          }
        },
        "attendees": {
          "$id": "40",
          "$values": []
        },
        "resources": {
          "$id": "41",
          "$values": []
        },
        "eventSeries": {
          "$id": "42",
          "$values": []
        }
      },
      {
        "$id": "43",
        "eventId": "e033e2fc-27c8-4a86-93d1-aa8bc7cb1a17",
        "eventOccurenceId": null,
        "creatorId": "d7965476-6b0d-4ee1-be67-c67626b7ced6",
        "calendarId": "64ff7caa-ca20-4d93-88e7-5798fb20d6c1",
        "eventTypeId": "07a68346-a516-45c7-9b7a-66f8fba11b3d",
        "startTime": "2025-06-14T14:00:00Z",
        "endTime": "2025-06-14T15:00:00Z",
        "startDate": "2025-06-14",
        "endDate": "2025-06-14",
        "timeZone": "Africa/Lagos",
        "title": "create",
        "description": "",
        "eventOwner": "Not Available",
        "meetingLink": null,
        "bannerImage": "https://vecap-bucket.s3.amazonaws.com/demo/calendar/default_banner.png",
        "meetingRoom": null,
        "additionalInfo": "",
        "noAttendeeHasResponded": true,
        "attendeesCount": 0,
        "responseCount": 0,
        "yesCount": 0,
        "noCount": 0,
        "maybeCount": 0,
        "isAllDay": false,
        "isSameDay": true,
        "venueAddress": null,
        "venueName": null,
        "eventClass": "Personal",
        "eventStatus": "Ended",
        "individualCalendar": null,
        "teamCalendar": null,
        "groupCalendar": null,
        "eventTeams": {
          "$id": "44",
          "$values": []
        },
        "eventGroups": {
          "$id": "45",
          "$values": []
        },
        "eventSettings": {
          "$id": "46",
          "visibility": "private",
          "eventOccurence": "None",
          "recurrenceEnd": null,
          "eventEnds": false,
          "reminders": {
            "$id": "47",
            "$values": []
          }
        },
        "attendees": {
          "$id": "48",
          "$values": []
        },
        "resources": {
          "$id": "49",
          "$values": []
        },
        "eventSeries": {
          "$id": "50",
          "$values": []
        }
      },
      {
        "$id": "51",
        "eventId": "b8691cae-5eee-4988-9c11-0b82508e3e18",
        "eventOccurenceId": null,
        "creatorId": "d7965476-6b0d-4ee1-be67-c67626b7ced6",
        "calendarId": "64ff7caa-ca20-4d93-88e7-5798fb20d6c1",
        "eventTypeId": "07a68346-a516-45c7-9b7a-66f8fba11b3d",
        "startTime": "2025-06-16T11:00:00Z",
        "endTime": "2025-06-16T12:00:00Z",
        "startDate": "2025-06-16",
        "endDate": "2025-06-16",
        "timeZone": "Africa/Lagos",
        "title": "yes",
        "description": "",
        "eventOwner": "Not Available",
        "meetingLink": "",
        "bannerImage": "https://vecapp-bucket-dev.s3.amazonaws.com/demo/calendar/8ac739e3-9524-486c-b97e-6b3b9e98c18d.png",
        "meetingRoom": "",
        "additionalInfo": "",
        "noAttendeeHasResponded": true,
        "attendeesCount": 0,
        "responseCount": 0,
        "yesCount": 0,
        "noCount": 0,
        "maybeCount": 0,
        "isAllDay": false,
        "isSameDay": true,
        "venueAddress": "",
        "venueName": "",
        "eventClass": "Personal",
        "eventStatus": "Ended",
        "individualCalendar": null,
        "teamCalendar": null,
        "groupCalendar": null,
        "eventTeams": {
          "$id": "52",
          "$values": []
        },
        "eventGroups": {
          "$id": "53",
          "$values": []
        },
        "eventSettings": {
          "$id": "54",
          "visibility": "private",
          "eventOccurence": "None",
          "recurrenceEnd": null,
          "eventEnds": false,
          "reminders": {
            "$id": "55",
            "$values": []
          }
        },
        "attendees": {
          "$id": "56",
          "$values": []
        },
        "resources": {
          "$id": "57",
          "$values": []
        },
        "eventSeries": {
          "$id": "58",
          "$values": []
        }
      },
      {
        "$id": "59",
        "eventId": "153fc24e-0774-4efc-9038-ff116e2597a8",
        "eventOccurenceId": null,
        "creatorId": "d7965476-6b0d-4ee1-be67-c67626b7ced6",
        "calendarId": "64ff7caa-ca20-4d93-88e7-5798fb20d6c1",
        "eventTypeId": "07a68346-a516-45c7-9b7a-66f8fba11b3d",
        "startTime": "2025-06-16T15:00:00Z",
        "endTime": "2025-06-16T16:00:00Z",
        "startDate": "2025-06-16",
        "endDate": "2025-06-16",
        "timeZone": "Africa/Lagos",
        "title": "Uat timezone",
        "description": "",
        "eventOwner": "Not Available",
        "meetingLink": null,
        "bannerImage": "https://vecap-bucket.s3.amazonaws.com/demo/calendar/default_banner.png",
        "meetingRoom": null,
        "additionalInfo": "",
        "noAttendeeHasResponded": true,
        "attendeesCount": 0,
        "responseCount": 0,
        "yesCount": 0,
        "noCount": 0,
        "maybeCount": 0,
        "isAllDay": false,
        "isSameDay": true,
        "venueAddress": null,
        "venueName": null,
        "eventClass": "Personal",
        "eventStatus": "Ended",
        "individualCalendar": null,
        "teamCalendar": null,
        "groupCalendar": null,
        "eventTeams": {
          "$id": "60",
          "$values": []
        },
        "eventGroups": {
          "$id": "61",
          "$values": []
        },
        "eventSettings": {
          "$id": "62",
          "visibility": "private",
          "eventOccurence": "None",
          "recurrenceEnd": null,
          "eventEnds": false,
          "reminders": {
            "$id": "63",
            "$values": []
          }
        },
        "attendees": {
          "$id": "64",
          "$values": []
        },
        "resources": {
          "$id": "65",
          "$values": []
        },
        "eventSeries": {
          "$id": "66",
          "$values": []
        }
      },
      {
        "$id": "67",
        "eventId": "2b3af066-7ea8-4e7e-8767-f370a8af091e",
        "eventOccurenceId": null,
        "creatorId": "d7965476-6b0d-4ee1-be67-c67626b7ced6",
        "calendarId": "11ca63aa-06dd-40e5-a7ff-96d7c24d99e6",
        "eventTypeId": "07a68346-a516-45c7-9b7a-66f8fba11b3d",
        "startTime": "2025-06-17T11:00:00Z",
        "endTime": "2025-06-17T12:00:00Z",
        "startDate": "2025-06-17",
        "endDate": "2025-06-17",
        "timeZone": "Africa/Lagos",
        "title": "lagos event.",
        "description": "finday",
        "eventOwner": "Not Available",
        "meetingLink": "",
        "bannerImage": "https://vecap-bucket.s3.amazonaws.com/demo/calendar/default_banner.png",
        "meetingRoom": "",
        "additionalInfo": "",
        "noAttendeeHasResponded": true,
        "attendeesCount": 0,
        "responseCount": 0,
        "yesCount": 0,
        "noCount": 0,
        "maybeCount": 0,
        "isAllDay": false,
        "isSameDay": true,
        "venueAddress": "",
        "venueName": "",
        "eventClass": "Group",
        "eventStatus": "Ended",
        "individualCalendar": null,
        "teamCalendar": null,
        "groupCalendar": null,
        "eventTeams": {
          "$id": "68",
          "$values": []
        },
        "eventGroups": {
          "$id": "69",
          "$values": []
        },
        "eventSettings": {
          "$id": "70",
          "visibility": "private",
          "eventOccurence": "None",
          "recurrenceEnd": null,
          "eventEnds": false,
          "reminders": {
            "$id": "71",
            "$values": []
          }
        },
        "attendees": {
          "$id": "72",
          "$values": []
        },
        "resources": {
          "$id": "73",
          "$values": []
        },
        "eventSeries": {
          "$id": "74",
          "$values": []
        }
      },
      {
        "$id": "75",
        "eventId": "7cc92e3e-1e15-4e60-88c6-c21defac1b89",
        "eventOccurenceId": null,
        "creatorId": "d7965476-6b0d-4ee1-be67-c67626b7ced6",
        "calendarId": "448edacd-857b-4369-99cd-e33e52d02acd",
        "eventTypeId": "07a68346-a516-45c7-9b7a-66f8fba11b3d",
        "startTime": "2025-06-17T13:00:00Z",
        "endTime": "2025-06-17T14:00:00Z",
        "startDate": "2025-06-17",
        "endDate": "2025-06-17",
        "timeZone": "Africa/Lagos",
        "title": "All",
        "description": "",
        "eventOwner": "Not Available",
        "meetingLink": "",
        "bannerImage": "https://vecap-bucket.s3.amazonaws.com/demo/calendar/default_banner.png",
        "meetingRoom": "",
        "additionalInfo": "",
        "noAttendeeHasResponded": true,
        "attendeesCount": 0,
        "responseCount": 0,
        "yesCount": 0,
        "noCount": 0,
        "maybeCount": 0,
        "isAllDay": false,
        "isSameDay": true,
        "venueAddress": "",
        "venueName": "",
        "eventClass": "Team",
        "eventStatus": "Ended",
        "individualCalendar": null,
        "teamCalendar": null,
        "groupCalendar": null,
        "eventTeams": {
          "$id": "76",
          "$values": []
        },
        "eventGroups": {
          "$id": "77",
          "$values": []
        },
        "eventSettings": {
          "$id": "78",
          "visibility": "private",
          "eventOccurence": "None",
          "recurrenceEnd": null,
          "eventEnds": false,
          "reminders": {
            "$id": "79",
            "$values": []
          }
        },
        "attendees": {
          "$id": "80",
          "$values": []
        },
        "resources": {
          "$id": "81",
          "$values": []
        },
        "eventSeries": {
          "$id": "82",
          "$values": []
        }
      }
    ]
  },
  "lastPage": 5,
  "totalItems": 50
}